TechnoAyanWallpaperdl/__init__.py
TechnoAyanWallpaperdl-0.0.6.dist-info/METADATA
TechnoAyanWallpaperdl-0.0.6.dist-info/WHEEL
TechnoAyanWallpaperdl-0.0.6.dist-info/top_level.txt
TechnoAyanWallpaperdl-0.0.6.dist-info/RECORD
